ppuri/__init__.py
ppuri/__main__.py
ppuri/component/__init__.py
ppuri/component/address.py
ppuri/component/authority.py
ppuri/component/fragment.py
ppuri/component/ipv4.py
ppuri/component/ipv6.py
ppuri/component/media_type.py
ppuri/component/path.py
ppuri/component/query.py
ppuri/component/scheme.py
ppuri/component/userinfo.py
ppuri/exception.py
ppuri/py.typed
ppuri/scheme/__init__.py
ppuri/scheme/aaa.py
ppuri/scheme/about.py
ppuri/scheme/coap.py
ppuri/scheme/crid.py
ppuri/scheme/data.py
ppuri/scheme/file.py
ppuri/scheme/http.py
ppuri/scheme/mailto.py
ppuri/scheme/url.py
ppuri/scheme/urn.py
ppuri/uri.py
ppuri-0.3.1.dist-info/LICENSE
ppuri-0.3.1.dist-info/WHEEL
ppuri-0.3.1.dist-info/METADATA
ppuri-0.3.1.dist-info/RECORD
