Metadata-Version: 2.1
Name: ppuri
Version: 0.3.1
Summary: A pyparsing based URI parser/scanner library
License: Apache-2.0
Author: Simon Kennedy
Author-email: sffjunkie+code@gmail.com
Requires-Python: >=3.10,<4.0
Classifier: License :: OSI Approved :: Apache Software License
Classifier: Programming Language :: Python :: 3
Classifier: Programming Language :: Python :: 3.10
Requires-Dist: click (>=8.1.3,<9.0.0)
Requires-Dist: pyparsing (>=3.0.9,<4.0.0)
